odoo/addons/minecraft_field_tellraw/__init__.py
odoo/addons/minecraft_field_tellraw/__manifest__.py
odoo/addons/minecraft_field_tellraw/static/src/js/field_registry.js
odoo/addons/minecraft_field_tellraw/static/src/js/field_utils.js
odoo/addons/minecraft_field_tellraw/static/src/js/minecraft_tellraw_field.js
odoo/addons/minecraft_field_tellraw/static/src/xml/minecraft_tellraw_field.xml
odoo/addons/minecraft_field_tellraw/views/assets.xml
odoo14_addon_minecraft_field_tellraw-14.0.1.0.1.dist-info/METADATA
odoo14_addon_minecraft_field_tellraw-14.0.1.0.1.dist-info/WHEEL
odoo14_addon_minecraft_field_tellraw-14.0.1.0.1.dist-info/top_level.txt
odoo14_addon_minecraft_field_tellraw-14.0.1.0.1.dist-info/RECORD
